{
    "color": {
        "background": {
            " ": {
                "$value": "#FFFFFF",
                "$type": "color"
            },
            "2": {
                "$value": "#F5F5F5",
                "$type": "color"
            }
        },
        "on-background": {
            " ": {
                "$value": "#262626",
                "$type": "color"
            },
            "menu": {
                "$value": "#f4f4f4",
                "$type": "color"
            },
            "active": {
                "$value": "#e6e8ef",
                "$type": "color"
            },
            "app-bar": {
                "$value": "#343434",
                "$type": "color"
            },
            "alternate": {
                "$value": "#737373",
                "$type": "color"
            },
            "icon-background": {
                "$value": "#BDBDBD",
                "$type": "color"
            },
            "decoration": {
                "$value": "#e5e5e5",
                "$type": "color"
            },
            "link": {
                " ": {
                    "$value": "#0266c2",
                    "$type": "color"
                },
                "hover": {
                    "$value": "#004b90",
                    "$type": "color"
                }
            },
            "table-header-dark": {
                "$value": "#444444",
                "$type": "color"
            },
            "iq-insights": {
                "$value": "#edf5ff",
                "$type": "color"
            }
        }
    }
}